pyMediaSort/SortTV.py
pyMediaSort/__init__.py
pyMediaSort/__main__.py
pyMediaSort-5.dist-info/LICENSE
pyMediaSort-5.dist-info/METADATA
pyMediaSort-5.dist-info/WHEEL
pyMediaSort-5.dist-info/entry_points.txt
pyMediaSort-5.dist-info/top_level.txt
pyMediaSort-5.dist-info/RECORD
