Metadata-Version: 2.1
Name: pyMediaSort
Version: 5
Summary: Package for sorting media into Plex directory structure
Home-page: https://github.com/christopherwallis/pyMediaSort
Author: Christopher Wallis
Author-email: christopher.wallis@gmail.com
License: UNKNOWN
Keywords: sort media tv video plex
Platform: UNKNOWN
Classifier: Development Status :: 4 - Beta
Classifier: Environment :: Console
Classifier: Intended Audience :: End Users/Desktop
Classifier: License :: OSI Approved :: GNU General Public License v3 (GPLv3)
Classifier: Operating System :: OS Independent
Classifier: Programming Language :: Python :: 3 :: Only
Requires-Python: ~=3.7
License-File: LICENSE
